imagefactory/__init__.py
imagefactory/cli.py
imagefactory/imagefactory.py
imagefactory/tests/__init__.py
imagefactory/tests/test_cli.py
imagefactory/tests/test_imagefactory.py
imagefactory-0.1.0.dist-info/DESCRIPTION.rst
imagefactory-0.1.0.dist-info/METADATA
imagefactory-0.1.0.dist-info/RECORD
imagefactory-0.1.0.dist-info/WHEEL
imagefactory-0.1.0.dist-info/entry_points.txt
imagefactory-0.1.0.dist-info/metadata.json
imagefactory-0.1.0.dist-info/top_level.txt
