Metadata-Version: 2.0
Name: imagefactory
Version: 0.1.0
Summary: Python package for creating test images.
Home-page: https://github.com/jaantollander/imagefactory
Author: Jaan Tollander de Balsch
Author-email: jaan.tollander@gmail.com
License: MIT license
Keywords: imagefactory
Platform: UNKNOWN
Classifier: Development Status :: 2 - Pre-Alpha
Classifier: Intended Audience :: Developers
Classifier: License :: OSI Approved :: MIT License
Classifier: Natural Language :: English
Classifier: Programming Language :: Python :: 3
Classifier: Programming Language :: Python :: 3.3
Classifier: Programming Language :: Python :: 3.4
Classifier: Programming Language :: Python :: 3.5
Requires-Dist: Pillow
Requires-Dist: click
Provides-Extra: SVG
Requires-Dist: svgwrite; extra == 'SVG'
